{
  "term_id": "insider-trading",
  "name_ko": "내부자거래",
  "name_en": "insider trading",
  "aliases": [],
  "subject": "corporate_law",
  "unit": "company_law",
  "definition": "회사 내부자가 미공개 중요 정보를 이용해 주식을 매매하는 행위. 금지된다.",
  "formula": null,
  "difficulty": "intermediate",
  "confusable_with": [
    {
      "term_id": "short-swing-profit",
      "reason": "내부자거래는 정보 이용, 단기매매차익은 시점만 보는 객관적 규제"
    }
  ],
  "prerequisite_terms": [],
  "example": null,
  "rights_status": "self_generated",
  "review_status": "ai_draft"
}
